agentic_threat_hunting_framework-0.5.2.dist-info/licenses/LICENSE
athf/__init__.py
athf/__version__.py
athf/cli.py
athf/plugin_system.py
athf/agents/__init__.py
athf/agents/base.py
athf/agents/llm/__init__.py
athf/agents/llm/hunt_researcher.py
athf/agents/llm/hypothesis_generator.py
athf/commands/__init__.py
athf/commands/agent.py
athf/commands/context.py
athf/commands/env.py
athf/commands/hunt.py
athf/commands/init.py
athf/commands/investigate.py
athf/commands/research.py
athf/commands/similar.py
athf/commands/splunk.py
athf/core/__init__.py
athf/core/attack_matrix.py
athf/core/hunt_manager.py
athf/core/hunt_parser.py
athf/core/investigation_parser.py
athf/core/research_manager.py
athf/core/splunk_client.py
athf/core/template_engine.py
athf/core/web_search.py
athf/data/__init__.py
athf/data/docs/CHANGELOG.md
athf/data/docs/CLI_REFERENCE.md
athf/data/docs/INSTALL.md
athf/data/docs/README.md
athf/data/docs/environment.md
athf/data/docs/getting-started.md
athf/data/docs/level4-agentic-workflows.md
athf/data/docs/lock-pattern.md
athf/data/docs/maturity-model.md
athf/data/docs/why-athf.md
athf/data/hunts/FORMAT_GUIDELINES.md
athf/data/hunts/H-0001.md
athf/data/hunts/H-0002.md
athf/data/hunts/H-0003.md
athf/data/hunts/README.md
athf/data/integrations/MCP_CATALOG.md
athf/data/integrations/README.md
athf/data/integrations/quickstart/splunk.md
athf/data/knowledge/hunting-knowledge.md
athf/data/prompts/README.md
athf/data/prompts/ai-workflow.md
athf/data/prompts/basic-prompts.md
athf/data/templates/HUNT_LOCK.md
athf/utils/__init__.py
agentic_threat_hunting_framework-0.5.2.dist-info/METADATA
agentic_threat_hunting_framework-0.5.2.dist-info/WHEEL
agentic_threat_hunting_framework-0.5.2.dist-info/entry_points.txt
agentic_threat_hunting_framework-0.5.2.dist-info/top_level.txt
agentic_threat_hunting_framework-0.5.2.dist-info/RECORD
