Metadata-Version: 2.4
Name: agentic-threat-hunting-framework
Version: 0.5.2
Summary: Agentic Threat Hunting Framework - Memory and AI for threat hunters
Author-email: Sydney Marrone <athf@nebulock.io>
Maintainer-email: Sydney Marrone <athf@nebulock.io>
License: MIT
Project-URL: Homepage, https://github.com/Nebulock-Inc/agentic-threat-hunting-framework
Project-URL: Documentation, https://github.com/Nebulock-Inc/agentic-threat-hunting-framework/tree/main/docs
Project-URL: Repository, https://github.com/Nebulock-Inc/agentic-threat-hunting-framework
Project-URL: Issues, https://github.com/Nebulock-Inc/agentic-threat-hunting-framework/issues
Project-URL: Discussions, https://github.com/Nebulock-Inc/agentic-threat-hunting-framework/discussions
Keywords: threat-hunting,security,cybersecurity,mitre-attack,detection-engineering,soc,blue-team,incident-response,threat-intelligence,agentic-ai
Classifier: Development Status :: 3 - Alpha
Classifier: Intended Audience :: Information Technology
Classifier: Intended Audience :: System Administrators
Classifier: Topic :: Security
Classifier: Topic :: System :: Monitoring
Classifier: License :: OSI Approved :: MIT License
Classifier: Programming Language :: Python :: 3
Classifier: Programming Language :: Python :: 3.8
Classifier: Programming Language :: Python :: 3.9
Classifier: Programming Language :: Python :: 3.10
Classifier: Programming Language :: Python :: 3.11
Classifier: Programming Language :: Python :: 3.12
Classifier: Programming Language :: Python :: 3.13
Classifier: Operating System :: OS Independent
Classifier: Environment :: Console
Requires-Python: >=3.8
License-File: LICENSE
Requires-Dist: click>=8.0.0
Requires-Dist: pyyaml>=6.0
Requires-Dist: rich>=10.0.0
Requires-Dist: jinja2>=3.0.0
Requires-Dist: python-dotenv>=0.19.0
Requires-Dist: importlib_resources>=5.0.0; python_version < "3.9"
Provides-Extra: dev
Requires-Dist: pytest>=7.0.0; extra == "dev"
Requires-Dist: pytest-cov>=4.0.0; extra == "dev"
Requires-Dist: flake8>=6.0.0; extra == "dev"
Requires-Dist: mypy>=1.0.0; extra == "dev"
Requires-Dist: black>=23.0.0; extra == "dev"
Requires-Dist: isort>=5.12.0; extra == "dev"
Requires-Dist: bandit[toml]>=1.7.0; extra == "dev"
Requires-Dist: pre-commit>=3.0.0; extra == "dev"
Requires-Dist: types-PyYAML>=6.0.0; extra == "dev"
Provides-Extra: docs
Requires-Dist: mkdocs>=1.5.0; extra == "docs"
Requires-Dist: mkdocs-material>=9.0.0; extra == "docs"
Provides-Extra: similarity
Requires-Dist: scikit-learn>=1.0.0; extra == "similarity"
Provides-Extra: splunk
Requires-Dist: requests>=2.25.0; extra == "splunk"
Dynamic: license-file
